Metadata-Version: 1.1
Name: nowatermark
Version: 0.0.1
Summary: remove image watermark
Home-page: https://github.com/sixquant/nowatermark
Author: caviler
Author-email: caviler@gmail.com
License: BSD
Keywords: remove watermark
Platform: UNKNOWN
Classifier: Development Status :: 3 - Alpha
Classifier: Programming Language :: Python :: 2.6
Classifier: Programming Language :: Python :: 2.7
Classifier: Programming Language :: Python :: 3.4
Classifier: Programming Language :: Python :: 3.5
Classifier: Programming Language :: Python :: 3.6
Classifier: License :: OSI Approved :: BSD License
